<?xml version="1.0" encoding="utf-8"?>
<addresss>
    <!--序厅区  0是直接关 1是延迟1秒关-->
    <address id="1">
        <name>筒灯1路(地址1,第1路)</name>
        <addre>01</addre>
        <includecomputer>0</includecomputer>
        <area>序厅区</area>
        <fewWays>3路</fewWays>
        <url>http://200.1.1.100</url>
        <port>8001</port>>
    </address>
    <address id="2">
        <name>展项+吊顶灯带1路(地址1,第2路)</name>
        <addre>01</addre>
        <includecomputer>0</includecomputer>
        <area>序厅区</area>
        <fewWays>7路</fewWays>
        <url>http://200.1.1.100</url>
        <port>8001</port>>
    </address>
    <address id="3">
        <name>环绕灯带1路(地址1，第3路)</name>
        <addre>01</addre>
        <includecomputer>0</includecomputer>
        <area>序厅区</area>
        <fewWays>12路</fewWays>
        <url>http://200.1.1.100</url>
        <port>8001</port>>
    </address>
    <address id="4">
        <name>AI迎宾墙</name>
        <addre>03</addre>
        <includecomputer>1</includecomputer>
        <area>序厅区</area>
        <fewWays>12路</fewWays>
        <url>http://192.168.1.16</url>
        <port>8001</port>>
    </address>
    <address id="5">
        <name>轨道灯1路(地址1，第5路)</name>
        <addre>01</addre>
        <includecomputer>0</includecomputer>
        <area>序厅区</area>
        <fewWays>5路</fewWays>
        <url>http://200.1.1.100</url>
        <port>8001</port>>
    </address>
    <!--视觉区-->
    <address id="1">
        <name>灯带1路(地址1，第6路)</name>
        <addre>01</addre>
        <includecomputer>0</includecomputer>
        <area>视觉区</area>
        <fewWays>2路</fewWays>
        <url>http://200.1.1.100</url>
        <port>8001</port>>
    </address>
    <address id="2">
        <name>动感火柴人(地址1，第7路))</name>
        <addre>03</addre>
        <includecomputer>1</includecomputer>
        <area>视觉区</area>
        <fewWays>11路</fewWays>
        <url>http://192.168.1.21</url>
        <port>8001</port>>
    </address>
    <address id="2">
        <name>cv展项</name>
        <addre>03</addre>
        <includecomputer>0</includecomputer>
        <area>视觉区</area>
        <fewWays>11路</fewWays>
        <url>http://192.168.1.22</url>
        <port>8001</port>>
    </address>
    <address id="3">
        <name>顶部软膜灯1路(地址1,第8路)</name>
        <addre>02</addre>
        <includecomputer>0</includecomputer>
        <area>视觉区</area>
        <fewWays>1路</fewWays>
        <url>http://200.1.1.100</url>
        <port>8001</port>>
    </address>
    <!--语音区-->
    <address id="1">
        <name>轨道灯1路(地址1，第9路)</name>
        <addre>02</addre>
        <includecomputer>0</includecomputer>
        <area>语音区</area>
        <fewWays>4路</fewWays>
        <url>http://200.1.1.100</url>
        <port>8001</port>>
    </address>
    <address id="2">
        <name>说好普通话</name>
        <addre>03</addre>
        <includecomputer>1</includecomputer>
        <area>语音区</area>
        <fewWays>8路</fewWays>
        <url>http://192.168.1.18</url>
        <port>8001</port>>
    </address>
    <address id="2">
        <name>变声电话</name>
        <addre>03</addre>
        <includecomputer>1</includecomputer>
        <area>语音区</area>
        <fewWays>8路</fewWays>
        <url>http://192.168.1.19</url>
        <port>8001</port>>
    </address>
    <!--生态区-->
    <address id="1">
        <name>灯带1路(地址1，第11路)</name>
        <addre>02</addre>
        <includecomputer>0</includecomputer>
        <area>生态区</area>
        <fewWays>3路</fewWays>
        <url>http://200.1.1.100</url>
        <port>8001</port>>
    </address>
    <address id="2">
        <name>轨道灯1路(地址1，第12路)</name>
        <addre>02</addre>
        <includecomputer>0</includecomputer>
        <area>生态区</area>
        <fewWays>5路</fewWays>
        <url>http://200.1.1.100</url>
        <port>8001</port>>
    </address>
    <address id="3">
        <name>魔墙</name>
        <addre>03</addre>
        <includecomputer>1</includecomputer>
        <area>生态区</area>
        <fewWays>5路</fewWays>
        <url>http://192.168.1.17</url>
        <port>8001</port>>
    </address>
    <!--尾厅区-->
    <address id="1">
        <name>轨道灯1路(地址2，第2路)</name>
        <addre>01</addre>
        <includecomputer>0</includecomputer>
        <area>尾厅区</area>
        <fewWays>9路</fewWays>
        <url>http://200.1.1.100</url>
        <port>8001</port>>
    </address>
    <address id="2">
         <name>灯带1路(地址2，第3路)</name>
         <addre>01</addre>
         <includecomputer>0</includecomputer>
         <area>尾厅区</area>
         <fewWays>4路</fewWays>
        <url>http://200.1.1.100</url>
         <port>8001</port>>
    </address>
    <address id="3">
        <name>留言墙</name>
        <addre>02</addre>
        <includecomputer>1</includecomputer>
        <area>尾厅区</area>
        <fewWays>4路</fewWays>
        <url>http://192.168.1.20</url>
        <port>8001</port>>
    </address>
</addresss>
